lepmlutils/__init__.py
lepmlutils/general/__init__.py
lepmlutils/general/audio.py
lepmlutils/general/help.py
lepmlutils/lgbmutils/__init__.py
lepmlutils/lgbmutils/graphics.py
lepmlutils/lgbmutils/help.py
lepmlutils/pdutils/__init__.py
lepmlutils/pdutils/addcoltfm.py
lepmlutils/pdutils/badindicatortfm.py
lepmlutils/pdutils/categorizetfm.py
lepmlutils/pdutils/classifiertfm.py
lepmlutils/pdutils/coltag.py
lepmlutils/pdutils/droptfm.py
lepmlutils/pdutils/estmode.py
lepmlutils/pdutils/funcreplacetfm.py
lepmlutils/pdutils/globals.py
lepmlutils/pdutils/graphics.py
lepmlutils/pdutils/help.py
lepmlutils/pdutils/imputer.py
lepmlutils/pdutils/internal.py
lepmlutils/pdutils/lag.py
lepmlutils/pdutils/lepdataframe.py
lepmlutils/pdutils/medianreplacetfm.py
lepmlutils/pdutils/mergeddataframe.py
lepmlutils/pdutils/onehottfm.py
lepmlutils/pdutils/partition.py
lepmlutils/pdutils/repeatabletfm.py
lepmlutils/pdutils/skewtfm.py
lepmlutils/pdutils/taggeddataframe.py
lepmlutils/pdutils/test_addcoltfm.py
lepmlutils/pdutils/test_badindicatortfm.py
lepmlutils/pdutils/test_categorizetfm.py
lepmlutils/pdutils/test_droptfm.py
lepmlutils/pdutils/test_funcreplacetfm.py
lepmlutils/pdutils/test_help.py
lepmlutils/pdutils/test_imputer.py
lepmlutils/pdutils/test_internal.py
lepmlutils/pdutils/test_lag.py
lepmlutils/pdutils/test_lepdataframe.py
lepmlutils/pdutils/test_medianreplacetfm.py
lepmlutils/pdutils/test_mergeddataframe.py
lepmlutils/pdutils/test_onehottfm.py
lepmlutils/pdutils/test_partition.py
lepmlutils/pdutils/test_skewtfm.py
lepmlutils/pdutils/test_taggeddataframe.py
lepmlutils/pdutils/test_typetfm.py
lepmlutils/pdutils/transform.py
lepmlutils/pdutils/typetfm.py
lepmlutils/pdutils/votingregressor.py
lepmlutils/pdutils/persister/__init__.py
lepmlutils/pdutils/persister/pairpersister.py
lepmlutils/pdutils/persister/persister.py
lepmlutils/pdutils/persister/profile.py
lepmlutils/pdutils/persister/test_pairpersister.py
lepmlutils/pdutils/persister/test_persister.py
lepmlutils-2.5.20.dist-info/LICENSE
lepmlutils-2.5.20.dist-info/METADATA
lepmlutils-2.5.20.dist-info/WHEEL
lepmlutils-2.5.20.dist-info/top_level.txt
lepmlutils-2.5.20.dist-info/RECORD
