Metadata-Version: 2.1
Name: lepmlutils
Version: 2.5.20
Summary: A machine learning utility package
Home-page: https://github.com/Lewington-pitsos/mlutils
Author: Louka Ewington-Pitsos
Author-email: lewington@student.unimelb.edu.au
License: UNKNOWN
Platform: UNKNOWN
Classifier: Programming Language :: Python :: 3
Classifier: License :: OSI Approved :: MIT License
Classifier: Operating System :: OS Independent
Requires-Dist: sklearn
Requires-Dist: xgboost
